README
setup.py
BatchlyApi/APIException.py
BatchlyApi/APIHelper.py
BatchlyApi/Configuration.py
BatchlyApi/CustomAuthUtility.py
BatchlyApi/__init__.py
BatchlyApi/Controllers/AccountsController.py
BatchlyApi/Controllers/DataStoresController.py
BatchlyApi/Controllers/JobsController.py
BatchlyApi/Controllers/ProcessorsController.py
BatchlyApi/Controllers/ProjectsController.py
BatchlyApi/Controllers/RunsController.py
BatchlyApi/Controllers/__init__.py
BatchlyApi/Models/AccountModel.py
BatchlyApi/Models/AddAWSAccountRequest.py
BatchlyApi/Models/AddParameterGroupRequest.py
BatchlyApi/Models/AddProcessorRequest.py
BatchlyApi/Models/AddS3DataStoreRequest.py
BatchlyApi/Models/ApiErrorResponse.py
BatchlyApi/Models/CreateJobRequest.py
BatchlyApi/Models/CreateProjectRequest.py
BatchlyApi/Models/CustomImage.py
BatchlyApi/Models/DescribeJobModel.py
BatchlyApi/Models/DescribeParameterGroupResponse.py
BatchlyApi/Models/ExecuteJobRequest.py
BatchlyApi/Models/JobModel.py
BatchlyApi/Models/KeyValuePairStringString.py
BatchlyApi/Models/Language.py
BatchlyApi/Models/OperatingSystem.py
BatchlyApi/Models/Parameter.py
BatchlyApi/Models/Platform.py
BatchlyApi/Models/ProcessorModel.py
BatchlyApi/Models/ProjectModel.py
BatchlyApi/Models/RequestType.py
BatchlyApi/Models/ResponseType.py
BatchlyApi/Models/RunModel.py
BatchlyApi/Models/Status.py
BatchlyApi/Models/UpdateProjectRequest.py
BatchlyApi/Models/ValidationItem.py
BatchlyApi/Models/VpcDetails.py
BatchlyApi/Models/__init__.py
batchly_api.egg-info/PKG-INFO
batchly_api.egg-info/SOURCES.txt
batchly_api.egg-info/dependency_links.txt
batchly_api.egg-info/requires.txt
batchly_api.egg-info/top_level.txt