Metadata-Version: 1.1
Name: batchly-api
Version: 0.7.2
Summary: Batchly API SDK for integration with the REST endpoint
Home-page: http://www.batchly.net
Author: Batchly Support
Author-email: support@batchly.net
License: MIT
Keywords: batchly api sdk rest
Platform: UNKNOWN
Classifier: Development Status :: 5 - Production/Stable
Classifier: Intended Audience :: Developers
Classifier: Topic :: Internet :: WWW/HTTP :: Dynamic Content
Classifier: License :: OSI Approved :: MIT License
Classifier: Programming Language :: Python :: 2
Classifier: Programming Language :: Python :: 2.6
Classifier: Programming Language :: Python :: 2.7
